mcp_sql_adapter/.python-version
mcp_sql_adapter/__init__.py
mcp_sql_adapter/__main__.py
mcp_sql_adapter/server.py
mcp_sql_adapter-1.0.0.dist-info/METADATA
mcp_sql_adapter-1.0.0.dist-info/WHEEL
mcp_sql_adapter-1.0.0.dist-info/entry_points.txt
mcp_sql_adapter-1.0.0.dist-info/licenses/LICENSE
mcp_sql_adapter-1.0.0.dist-info/RECORD
