Metadata-Version: 2.4
Name: mcp-sql-adapter
Version: 1.0.0
Summary: A read-only MCP adapter for interacting with SQL databases.
Author-email: Shubham Kale <shubhamkale54@gmail.com>
License: MIT License
License-File: LICENSE
Keywords: adapter,database,llm,mcp,mysql,sql
Classifier: Development Status :: 3 - Alpha
Classifier: Intended Audience :: Developers
Classifier: License :: OSI Approved :: MIT License
Classifier: Programming Language :: Python :: 3.13
Classifier: Topic :: Database
Classifier: Topic :: Software Development :: Libraries
Requires-Python: >=3.10
Requires-Dist: mcp[cli]>=1.6.0
Requires-Dist: psycopg2-binary>=2.9.10
Requires-Dist: pymysql>=1.1.1
